pywgett/__init__.py
pywgett/cli.py
pywgett/download.py
pywgett/utils.py
pywgett-1.0.2.dist-info/LICENSE
pywgett-1.0.2.dist-info/METADATA
pywgett-1.0.2.dist-info/WHEEL
pywgett-1.0.2.dist-info/entry_points.txt
pywgett-1.0.2.dist-info/top_level.txt
pywgett-1.0.2.dist-info/RECORD
