Metadata-Version: 2.1
Name: pywgett
Version: 1.0.2
Summary: Download utility as an easy way to get files from the net
Home-page: https://github.com/ktechhub/pywgett
Author: Ktechhub
Author-email: mm@ktechhub.com
License: MIT
Keywords: download utility wget pywgett pywget pywgett.py pywget.py
Classifier: License :: OSI Approved :: MIT License
Classifier: Intended Audience :: Developers
Classifier: Programming Language :: Python :: 3.12
Classifier: Programming Language :: Python :: 3.11
Classifier: Programming Language :: Python :: 3.10
Classifier: Programming Language :: Python :: 3.9
Classifier: Programming Language :: Python :: 3.8
Classifier: Programming Language :: Python :: 3.7
Classifier: Programming Language :: Python :: 3.6
Requires-Python: >=3.6
License-File: LICENSE
Requires-Dist: click
Requires-Dist: requests
